CAT/__init__.py
CAT/__version__.py
CAT/_mol_str_parser.py
CAT/base.py
CAT/distribution.py
CAT/frozen_settings.py
CAT/gen_job_manager.py
CAT/jobs.py
CAT/logger.py
CAT/mol_utils.py
CAT/multi_ligand.py
CAT/py.typed
CAT/recipes.py
CAT/settings_dataframe.py
CAT/test_utils.py
CAT/thermo_chem.py
CAT/utils.py
CAT/attachment/__init__.py
CAT/attachment/as_array.py
CAT/attachment/core_anchoring.py
CAT/attachment/distribution.py
CAT/attachment/distribution_brute.py
CAT/attachment/distribution_utils.py
CAT/attachment/dye.py
CAT/attachment/edge_distance.py
CAT/attachment/ligand_anchoring.py
CAT/attachment/ligand_attach.py
CAT/attachment/ligand_opt.py
CAT/attachment/mol_split_cm.py
CAT/attachment/optimize_rotmat.py
CAT/attachment/perp_surface.py
CAT/attachment/qd_opt.py
CAT/attachment/remove_atoms_cm.py
CAT/attachment/substitution_symmetry.py
CAT/data/__init__.py
CAT/data/CORES/NDI.xyz
CAT/data/CORES/__init__.py
CAT/data/CORES/benzene.xyz
CAT/data/LIGANDS/__init__.py
CAT/data/LIGANDS/ash3.xyz
CAT/data/LIGANDS/ethyne.xyz
CAT/data/LIGANDS/hcl.xyz
CAT/data/LIGANDS/hcn.xyz
CAT/data/LIGANDS/hoh.xyz
CAT/data/LIGANDS/hsh.xyz
CAT/data/LIGANDS/methanol.xyz
CAT/data/LIGANDS/nh3.xyz
CAT/data/coskf/Acetone.coskf
CAT/data/coskf/Acetonitrile.coskf
CAT/data/coskf/DMF.coskf
CAT/data/coskf/DMSO.coskf
CAT/data/coskf/EtOAc.coskf
CAT/data/coskf/Ethanol.coskf
CAT/data/coskf/Hexane.coskf
CAT/data/coskf/Toluene.coskf
CAT/data/coskf/Water.coskf
CAT/data/coskf/__init__.py
CAT/data/coskf/misc/Hydronium.coskf
CAT/data/templates/__init__.py
CAT/data/templates/crs.yaml
CAT/data/templates/qd.yaml
CAT/data/templates/settings_blacklist.yaml
CAT/data/templates/smiles.yaml
CAT/data_handling/__init__.py
CAT/data_handling/anchor_parsing.py
CAT/data_handling/entry_points.py
CAT/data_handling/mol_import.py
CAT/data_handling/mol_to_file.py
CAT/data_handling/str_to_func.py
CAT/data_handling/update_qd_df.py
CAT/data_handling/validate_ff.py
CAT/data_handling/validate_input.py
CAT/data_handling/validate_mol.py
nlesc_CAT-1.1.0.dist-info/LICENSE.md
nlesc_CAT-1.1.0.dist-info/METADATA
nlesc_CAT-1.1.0.dist-info/WHEEL
nlesc_CAT-1.1.0.dist-info/entry_points.txt
nlesc_CAT-1.1.0.dist-info/top_level.txt
nlesc_CAT-1.1.0.dist-info/RECORD
